{
  "index": 4,
  "timestamp": "2026-03-11T10:54:54.306Z",
  "chain": "patterns",
  "data": {
    "type": "pattern",
    "source": "model-c",
    "event": "accuracy-update",
    "patternId": "pattern-1773226494257-382wkwq6z",
    "context": {
      "timeOfDay": 7,
      "dayOfWeek": 2,
      "tags": [
        "build",
        "pipeline"
      ],
      "chain": "decision",
      "recentDecisions": 1
    },
    "prediction": {
      "type": "tactical",
      "title": "Focus on optimize",
      "confidence": 0.3,
      "evidence": [
        "optimize",
        "build"
      ]
    },
    "occurrences": 3,
    "accuracy": 1,
    "totalPredictions": 1,
    "correctPredictions": 1,
    "tags": [
      "model-c",
      "pattern",
      "accuracy-update"
    ],
    "timestamp": "2026-03-11T10:54:54.268Z"
  },
  "prev_hash": "eb36cce7775374310b962a97c08851355b0b4d1939ed399f768c1d9186e89675",
  "hash": "37b1d1d0ed1c8183e1ea97dcd000b36390213f5b594d6aa69d3aabf2ae93fc2b"
}